{"version":{"fullVersion":"1.6.1","major":"1","minor":"6","patch":"1"},"meta":{"flags":["experimentalData"]},"collections":[{"name":"home","label":"Home","path":"content/home","format":"json","ui":{"filename":{"readonly":true}},"fields":[{"name":"language","label":"Language","type":"string","options":[{"value":"en","label":"English"},{"value":"es","label":"Español"},{"value":"fr","label":"Français"}],"required":true,"namespace":["home","language"],"searchable":true,"uid":false},{"name":"heroTitle","label":"Hero Title","type":"string","required":true,"namespace":["home","heroTitle"],"searchable":true,"uid":false},{"name":"heroSubtitle","label":"Hero Subtitle","type":"string","required":true,"ui":{"component":"textarea"},"namespace":["home","heroSubtitle"],"searchable":true,"uid":false},{"name":"ctaLabel","label":"CTA Label","type":"string","required":true,"namespace":["home","ctaLabel"],"searchable":true,"uid":false}],"namespace":["home"]},{"name":"sections","label":"Sections","path":"content/sections","format":"mdx","fields":[{"name":"language","label":"Language","type":"string","options":[{"value":"en","label":"English"},{"value":"es","label":"Español"},{"value":"fr","label":"Français"}],"required":true,"namespace":["sections","language"],"searchable":true,"uid":false},{"name":"title","label":"Title","type":"string","required":true,"namespace":["sections","title"],"searchable":true,"uid":false},{"name":"excerpt","label":"Excerpt","type":"string","namespace":["sections","excerpt"],"searchable":true,"uid":false},{"name":"body","label":"Body","type":"rich-text","isBody":true,"namespace":["sections","body"],"searchable":true,"parser":{"type":"mdx"},"uid":false}],"namespace":["sections"]}],"config":{"media":{"tina":{"publicFolder":"public","mediaRoot":"uploads"}}}}